{
  "language_code": "de",
  "language_name": "German",
  "verbs": [
    {
      "infinitive": "sein",
      "translation_en": "to be",
      "tags": ["irregular", "auxiliary"],
      "tenses": {
        "präsens": {
          "mood": "indicativ",
          "forms": { "ich": "bin", "du": "bist", "er/sie/es": "ist", "wir": "sind", "ihr": "seid", "sie/Sie": "sind" }
        },
        "perfekt": {
          "mood": "indicativ", "auxiliary_verb": "sein", "past_participle": "gewesen",
          "forms": { "ich": "bin gewesen", "du": "bist gewesen", "er/sie/es": "ist gewesen", "wir": "sind gewesen", "ihr": "seid gewesen", "sie/Sie": "sind gewesen" }
        },
        "präteritum": {
          "mood": "indicativ",
          "forms": { "ich": "war", "du": "warst", "er/sie/es": "war", "wir": "waren", "ihr": "wart", "sie/Sie": "waren" }
        },
        "futur I": {
          "mood": "indicativ", "auxiliary_verb": "werden",
          "forms": { "ich": "werde sein", "du": "wirst sein", "er/sie/es": "wird sein", "wir": "werden sein", "ihr": "werdet sein", "sie/Sie": "werden sein" }
        },
        "konjunktiv II": {
          "mood": "konjunktiv",
          "forms": { "ich": "wäre", "du": "wärest", "er/sie/es": "wäre", "wir": "wären", "ihr": "wäret", "sie/Sie": "wären" }
        }
      }
    },
    {
      "infinitive": "haben",
      "translation_en": "to have",
      "tags": ["irregular", "auxiliary"],
      "tenses": {
        "präsens": {
          "mood": "indicativ",
          "forms": { "ich": "habe", "du": "hast", "er/sie/es": "hat", "wir": "haben", "ihr": "habt", "sie/Sie": "haben" }
        },
        "perfekt": {
          "mood": "indicativ", "auxiliary_verb": "haben", "past_participle": "gehabt",
          "forms": { "ich": "habe gehabt", "du": "hast gehabt", "er/sie/es": "hat gehabt", "wir": "haben gehabt", "ihr": "habt gehabt", "sie/Sie": "haben gehabt" }
        },
        "präteritum": {
          "mood": "indicativ",
          "forms": { "ich": "hatte", "du": "hattest", "er/sie/es": "hatte", "wir": "hatten", "ihr": "hattet", "sie/Sie": "hatten" }
        },
        "futur I": {
          "mood": "indicativ", "auxiliary_verb": "werden",
          "forms": { "ich": "werde haben", "du": "wirst haben", "er/sie/es": "wird haben", "wir": "werden haben", "ihr": "werdet haben", "sie/Sie": "werden haben" }
        },
        "konjunktiv II": {
          "mood": "konjunktiv",
          "forms": { "ich": "hätte", "du": "hättest", "er/sie/es": "hätte", "wir": "hätten", "ihr": "hättet", "sie/Sie": "hätten" }
        }
      }
    },
    {
      "infinitive": "mögen",
      "translation_en": "to like",
      "tags": ["irregular", "modal"],
      "tenses": {
        "präsens": {
          "mood": "indicativ",
          "forms": { "ich": "mag", "du": "magst", "er/sie/es": "mag", "wir": "mögen", "ihr": "mögt", "sie/Sie": "mögen" }
        },
        "perfekt": {
          "mood": "indicativ", "auxiliary_verb": "haben", "past_participle": "gemocht",
          "forms": { "ich": "habe gemocht", "du": "hast gemocht", "er/sie/es": "hat gemocht", "wir": "haben gemocht", "ihr": "habt gemocht", "sie/Sie": "haben gemocht" }
        },
        "präteritum": {
          "mood": "indicativ",
          "forms": { "ich": "mochte", "du": "mochtest", "er/sie/es": "mochte", "wir": "mochten", "ihr": "mochtet", "sie/Sie": "mochten" }
        },
        "futur I": {
          "mood": "indicativ", "auxiliary_verb": "werden",
          "forms": { "ich": "werde mögen", "du": "wirst mögen", "er/sie/es": "wird mögen", "wir": "werden mögen", "ihr": "werdet mögen", "sie/Sie": "werden mögen" }
        },
        "konjunktiv II": {
          "mood": "konjunktiv", "translation_en_tense": "would like",
          "forms": { "ich": "möchte", "du": "möchtest", "er/sie/es": "möchte", "wir": "möchten", "ihr": "möchtet", "sie/Sie": "möchten" }
        }
      }
    },
    {
      "infinitive": "gefallen",
      "translation_en": "to like (to be pleasing to)",
      "tags": ["irregular", "dative_subject"],
      "notes": "Used with a dative pronoun for the 'liker', e.g., 'es gefällt mir' (I like it). Auxiliary in Perfekt is 'haben'.",
      "tenses": {
        "präsens": {
          "mood": "indicativ",
          "forms": { "(er/sie/es)": "gefällt", "(sie/Sie Plural)": "gefallen" }
        },
        "perfekt": {
          "mood": "indicativ", "auxiliary_verb": "haben", "past_participle": "gefallen",
          "forms": { "(er/sie/es)": "hat gefallen", "(sie/Sie Plural)": "haben gefallen" }
        },
        "präteritum": {
          "mood": "indicativ",
          "forms": { "(er/sie/es)": "gefiel", "(sie/Sie Plural)": "gefielen" }
        },
        "futur I": {
          "mood": "indicativ", "auxiliary_verb": "werden",
          "forms": { "(er/sie/es)": "wird gefallen", "(sie/Sie Plural)": "werden gefallen" }
        },
        "konjunktiv II": {
          "mood": "konjunktiv",
          "forms": { "(er/sie/es)": "gefiele", "(sie/Sie Plural)": "gefielen" }
        }
      }
    },
    {
      "infinitive": "denken",
      "translation_en": "to think (process)",
      "tags": ["irregular"],
      "tenses": {
        "präsens": {
          "mood": "indicativ",
          "forms": { "ich": "denke", "du": "denkst", "er/sie/es": "denkt", "wir": "denken", "ihr": "denkt", "sie/Sie": "denken" }
        },
        "perfekt": {
          "mood": "indicativ", "auxiliary_verb": "haben", "past_participle": "gedacht",
          "forms": { "ich": "habe gedacht", "du": "hast gedacht", "er/sie/es": "hat gedacht", "wir": "haben gedacht", "ihr": "habt gedacht", "sie/Sie": "haben gedacht" }
        },
        "präteritum": {
          "mood": "indicativ",
          "forms": { "ich": "dachte", "du": "dachtest", "er/sie/es": "dachte", "wir": "dachten", "ihr": "dachtet", "sie/Sie": "dachten" }
        },
        "futur I": {
          "mood": "indicativ", "auxiliary_verb": "werden",
          "forms": { "ich": "werde denken", "du": "wirst denken", "er/sie/es": "wird denken", "wir": "werden denken", "ihr": "werdet denken", "sie/Sie": "werden denken" }
        },
        "konjunktiv II": {
          "mood": "konjunktiv",
          "forms": { "ich": "dächte", "du": "dächtest", "er/sie/es": "dächte", "wir": "dächten", "ihr": "dächtet", "sie/Sie": "dächten" }
        }
      }
    },
    {
      "infinitive": "glauben",
      "translation_en": "to believe/think (opinion)",
      "tags": ["regular"],
      "tenses": {
        "präsens": {
          "mood": "indicativ",
          "forms": { "ich": "glaube", "du": "glaubst", "er/sie/es": "glaubt", "wir": "glauben", "ihr": "glaubt", "sie/Sie": "glauben" }
        },
        "perfekt": {
          "mood": "indicativ", "auxiliary_verb": "haben", "past_participle": "geglaubt",
          "forms": { "ich": "habe geglaubt", "du": "hast geglaubt", "er/sie/es": "hat geglaubt", "wir": "haben geglaubt", "ihr": "habt geglaubt", "sie/Sie": "haben geglaubt" }
        },
        "präteritum": {
          "mood": "indicativ",
          "forms": { "ich": "glaubte", "du": "glaubtest", "er/sie/es": "glaubte", "wir": "glaubten", "ihr": "glaubtet", "sie/Sie": "glaubten" }
        },
        "futur I": {
          "mood": "indicativ", "auxiliary_verb": "werden",
          "forms": { "ich": "werde glauben", "du": "wirst glauben", "er/sie/es": "wird glauben", "wir": "werden glauben", "ihr": "werdet glauben", "sie/Sie": "werden glauben" }
        },
        "konjunktiv II": {
          "mood": "konjunktiv",
          "forms": { "ich": "glaubte", "du": "glaubtest", "er/sie/es": "glaubte", "wir": "glaubten", "ihr": "glaubtet", "sie/Sie": "glaubten" }
        }
      }
    },
    {
      "infinitive": "wissen",
      "translation_en": "to know (facts/skills)",
      "tags": ["irregular", "modal-like-present"],
      "tenses": {
        "präsens": {
          "mood": "indicativ",
          "forms": { "ich": "weiß", "du": "weißt", "er/sie/es": "weiß", "wir": "wissen", "ihr": "wisst", "sie/Sie": "wissen" }
        },
        "perfekt": {
          "mood": "indicativ", "auxiliary_verb": "haben", "past_participle": "gewusst",
          "forms": { "ich": "habe gewusst", "du": "hast gewusst", "er/sie/es": "hat gewusst", "wir": "haben gewusst", "ihr": "habt gewusst", "sie/Sie": "haben gewusst" }
        },
        "präteritum": {
          "mood": "indicativ",
          "forms": { "ich": "wusste", "du": "wusstest", "er/sie/es": "wusste", "wir": "wussten", "ihr": "wusstet", "sie/Sie": "wussten" }
        },
        "futur I": {
          "mood": "indicativ", "auxiliary_verb": "werden",
          "forms": { "ich": "werde wissen", "du": "wirst wissen", "er/sie/es": "wird wissen", "wir": "werden wissen", "ihr": "werdet wissen", "sie/Sie": "werden wissen" }
        },
        "konjunktiv II": {
          "mood": "konjunktiv",
          "forms": { "ich": "wüsste", "du": "wüsstest", "er/sie/es": "wüsste", "wir": "wüssten", "ihr": "wüsstet", "sie/Sie": "wüssten" }
        }
      }
    },
    {
      "infinitive": "kennen",
      "translation_en": "to know (people/places)",
      "tags": ["irregular"],
      "tenses": {
        "präsens": {
          "mood": "indicativ",
          "forms": { "ich": "kenne", "du": "kennst", "er/sie/es": "kennt", "wir": "kennen", "ihr": "kennt", "sie/Sie": "kennen" }
        },
        "perfekt": {
          "mood": "indicativ", "auxiliary_verb": "haben", "past_participle": "gekannt",
          "forms": { "ich": "habe gekannt", "du": "hast gekannt", "er/sie/es": "hat gekannt", "wir": "haben gekannt", "ihr": "habt gekannt", "sie/Sie": "haben gekannt" }
        },
        "präteritum": {
          "mood": "indicativ",
          "forms": { "ich": "kannte", "du": "kanntest", "er/sie/es": "kannte", "wir": "kannten", "ihr": "kanntet", "sie/Sie": "kannten" }
        },
        "futur I": {
          "mood": "indicativ", "auxiliary_verb": "werden",
          "forms": { "ich": "werde kennen", "du": "wirst kennen", "er/sie/es": "wird kennen", "wir": "werden kennen", "ihr": "werdet kennen", "sie/Sie": "werden kennen" }
        },
        "konjunktiv II": {
          "mood": "konjunktiv",
          "forms": { "ich": "kennte", "du": "kenntest", "er/sie/es": "kennte", "wir": "kennten", "ihr": "kenntet", "sie/Sie": "kennten" }
        }
      }
    },
    {
      "infinitive": "wollen",
      "translation_en": "to want",
      "tags": ["irregular", "modal"],
      "tenses": {
        "präsens": {
          "mood": "indicativ",
          "forms": { "ich": "will", "du": "willst", "er/sie/es": "will", "wir": "wollen", "ihr": "wollt", "sie/Sie": "wollen" }
        },
        "perfekt": {
          "mood": "indicativ", "auxiliary_verb": "haben", "past_participle": "gewollt", 
          "notes": "Often uses double infinitive in Perfekt if main verb present: 'ich habe gehen wollen'",
          "forms": { "ich": "habe gewollt", "du": "hast gewollt", "er/sie/es": "hat gewollt", "wir": "haben gewollt", "ihr": "habt gewollt", "sie/Sie": "haben gewollt" }
        },
        "präteritum": {
          "mood": "indicativ",
          "forms": { "ich": "wollte", "du": "wolltest", "er/sie/es": "wollte", "wir": "wollten", "ihr": "wolltet", "sie/Sie": "wollten" }
        },
        "futur I": {
          "mood": "indicativ", "auxiliary_verb": "werden",
          "forms": { "ich": "werde wollen", "du": "wirst wollen", "er/sie/es": "wird wollen", "wir": "werden wollen", "ihr": "werdet wollen", "sie/Sie": "werden wollen" }
        },
        "konjunktiv II": {
          "mood": "konjunktiv",
          "forms": { "ich": "wollte", "du": "wolltest", "er/sie/es": "wollte", "wir": "wollten", "ihr": "wolltet", "sie/Sie": "wollten" }
        }
      }
    },
    {
      "infinitive": "arbeiten",
      "translation_en": "to work",
      "tags": ["regular", "ending-et"],
      "tenses": {
        "präsens": {
          "mood": "indicativ",
          "forms": { "ich": "arbeite", "du": "arbeitest", "er/sie/es": "arbeitet", "wir": "arbeiten", "ihr": "arbeitet", "sie/Sie": "arbeiten" }
        },
        "perfekt": {
          "mood": "indicativ", "auxiliary_verb": "haben", "past_participle": "gearbeitet",
          "forms": { "ich": "habe gearbeitet", "du": "hast gearbeitet", "er/sie/es": "hat gearbeitet", "wir": "haben gearbeitet", "ihr": "habt gearbeitet", "sie/Sie": "haben gearbeitet" }
        },
        "präteritum": {
          "mood": "indicativ",
          "forms": { "ich": "arbeitete", "du": "arbeitetest", "er/sie/es": "arbeitete", "wir": "arbeiteten", "ihr": "arbeitetet", "sie/Sie": "arbeiteten" }
        },
        "futur I": {
          "mood": "indicativ", "auxiliary_verb": "werden",
          "forms": { "ich": "werde arbeiten", "du": "wirst arbeiten", "er/sie/es": "wird arbeiten", "wir": "werden arbeiten", "ihr": "werdet arbeiten", "sie/Sie": "werden arbeiten" }
        },
        "konjunktiv II": {
          "mood": "konjunktiv",
          "forms": { "ich": "arbeitete", "du": "arbeitetest", "er/sie/es": "arbeitete", "wir": "arbeiteten", "ihr": "arbeitetet", "sie/Sie": "arbeiteten" }
        }
      }
    },
    {
      "infinitive": "studieren",
      "translation_en": "to study (at university)",
      "tags": ["regular", "verb-ending-ieren"],
      "tenses": {
        "präsens": {
          "mood": "indicativ",
          "forms": { "ich": "studiere", "du": "studierst", "er/sie/es": "studiert", "wir": "studieren", "ihr": "studiert", "sie/Sie": "studieren" }
        },
        "perfekt": {
          "mood": "indicativ", "auxiliary_verb": "haben", "past_participle": "studiert",
          "forms": { "ich": "habe studiert", "du": "hast studiert", "er/sie/es": "hat studiert", "wir": "haben studiert", "ihr": "habt studiert", "sie/Sie": "haben studiert" }
        },
        "präteritum": {
          "mood": "indicativ",
          "forms": { "ich": "studierte", "du": "studiertest", "er/sie/es": "studierte", "wir": "studierten", "ihr": "studiertet", "sie/Sie": "studierten" }
        },
        "futur I": {
          "mood": "indicativ", "auxiliary_verb": "werden",
          "forms": { "ich": "werde studieren", "du": "wirst studieren", "er/sie/es": "wird studieren", "wir": "werden studieren", "ihr": "werdet studieren", "sie/Sie": "werden studieren" }
        },
        "konjunktiv II": {
          "mood": "konjunktiv",
          "forms": { "ich": "studierte", "du": "studiertest", "er/sie/es": "studierte", "wir": "studierten", "ihr": "studiertet", "sie/Sie": "studierten" }
        }
      }
    },
    {
      "infinitive": "lernen",
      "translation_en": "to learn/study (general)",
      "tags": ["regular"],
      "tenses": {
        "präsens": {
          "mood": "indicativ",
          "forms": { "ich": "lerne", "du": "lernst", "er/sie/es": "lernt", "wir": "lernen", "ihr": "lernt", "sie/Sie": "lernen" }
        },
        "perfekt": {
          "mood": "indicativ", "auxiliary_verb": "haben", "past_participle": "gelernt",
          "forms": { "ich": "habe gelernt", "du": "hast gelernt", "er/sie/es": "hat gelernt", "wir": "haben gelernt", "ihr": "habt gelernt", "sie/Sie": "haben gelernt" }
        },
        "präteritum": {
          "mood": "indicativ",
          "forms": { "ich": "lernte", "du": "lerntest", "er/sie/es": "lernte", "wir": "lernten", "ihr": "lerntet", "sie/Sie": "lernten" }
        },
        "futur I": {
          "mood": "indicativ", "auxiliary_verb": "werden",
          "forms": { "ich": "werde lernen", "du": "wirst lernen", "er/sie/es": "wird lernen", "wir": "werden lernen", "ihr": "werdet lernen", "sie/Sie": "werden lernen" }
        },
        "konjunktiv II": {
          "mood": "konjunktiv",
          "forms": { "ich": "lernte", "du": "lerntest", "er/sie/es": "lernte", "wir": "lernten", "ihr": "lerntet", "sie/Sie": "lernten" }
        }
      }
    },
    {
      "infinitive": "gehen",
      "translation_en": "to go",
      "tags": ["irregular"],
      "tenses": {
        "präsens": {
          "mood": "indicativ",
          "forms": { "ich": "gehe", "du": "gehst", "er/sie/es": "geht", "wir": "gehen", "ihr": "geht", "sie/Sie": "gehen" }
        },
        "perfekt": {
          "mood": "indicativ", "auxiliary_verb": "sein", "past_participle": "gegangen",
          "forms": { "ich": "bin gegangen", "du": "bist gegangen", "er/sie/es": "ist gegangen", "wir": "sind gegangen", "ihr": "seid gegangen", "sie/Sie": "sind gegangen" }
        },
        "präteritum": {
          "mood": "indicativ",
          "forms": { "ich": "ging", "du": "gingst", "er/sie/es": "ging", "wir": "gingen", "ihr": "gingt", "sie/Sie": "gingen" }
        },
        "futur I": {
          "mood": "indicativ", "auxiliary_verb": "werden",
          "forms": { "ich": "werde gehen", "du": "wirst gehen", "er/sie/es": "wird gehen", "wir": "werden gehen", "ihr": "werdet gehen", "sie/Sie": "werden gehen" }
        },
        "konjunktiv II": {
          "mood": "konjunktiv",
          "forms": { "ich": "ginge", "du": "gingest", "er/sie/es": "ginge", "wir": "gingen", "ihr": "ginget", "sie/Sie": "gingen" }
        }
      }
    },
    {
      "infinitive": "können",
      "translation_en": "to be able to (can)",
      "tags": ["irregular", "modal"],
      "tenses": {
        "präsens": {
          "mood": "indicativ",
          "forms": { "ich": "kann", "du": "kannst", "er/sie/es": "kann", "wir": "können", "ihr": "könnt", "sie/Sie": "können" }
        },
        "perfekt": {
          "mood": "indicativ", "auxiliary_verb": "haben", "past_participle": "gekonnt",
          "notes": "Often uses double infinitive in Perfekt if main verb present: 'ich habe gehen können'",
          "forms": { "ich": "habe gekonnt", "du": "hast gekonnt", "er/sie/es": "hat gekonnt", "wir": "haben gekonnt", "ihr": "habt gekonnt", "sie/Sie": "haben gekonnt" }
        },
        "präteritum": {
          "mood": "indicativ",
          "forms": { "ich": "konnte", "du": "konntest", "er/sie/es": "konnte", "wir": "konnten", "ihr": "konntet", "sie/Sie": "konnten" }
        },
        "futur I": {
          "mood": "indicativ", "auxiliary_verb": "werden",
          "forms": { "ich": "werde können", "du": "wirst können", "er/sie/es": "wird können", "wir": "werden können", "ihr": "werdet können", "sie/Sie": "werden können" }
        },
        "konjunktiv II": {
          "mood": "konjunktiv",
          "forms": { "ich": "könnte", "du": "könntest", "er/sie/es": "könnte", "wir": "könnten", "ihr": "könntet", "sie/Sie": "könnten" }
        }
      }
    },
    {
      "infinitive": "essen",
      "translation_en": "to eat",
      "tags": ["irregular", "stem-vowel-change"],
      "tenses": {
        "präsens": {
          "mood": "indicativ",
          "forms": { "ich": "esse", "du": "isst", "er/sie/es": "isst", "wir": "essen", "ihr": "esst", "sie/Sie": "essen" }
        },
        "perfekt": {
          "mood": "indicativ", "auxiliary_verb": "haben", "past_participle": "gegessen",
          "forms": { "ich": "habe gegessen", "du": "hast gegessen", "er/sie/es": "hat gegessen", "wir": "haben gegessen", "ihr": "habt gegessen", "sie/Sie": "haben gegessen" }
        },
        "präteritum": {
          "mood": "indicativ",
          "forms": { "ich": "aß", "du": "aßt", "er/sie/es": "aß", "wir": "aßen", "ihr": "aßt", "sie/Sie": "aßen" }
        },
        "futur I": {
          "mood": "indicativ", "auxiliary_verb": "werden",
          "forms": { "ich": "werde essen", "du": "wirst essen", "er/sie/es": "wird essen", "wir": "werden essen", "ihr": "werdet essen", "sie/Sie": "werden essen" }
        },
        "konjunktiv II": {
          "mood": "konjunktiv",
          "forms": { "ich": "äße", "du": "äßest", "er/sie/es": "äße", "wir": "äßen", "ihr": "äßet", "sie/Sie": "äßen" }
        }
      }
    },
    {
      "infinitive": "trinken",
      "translation_en": "to drink",
      "tags": ["irregular"],
      "tenses": {
        "präsens": {
          "mood": "indicativ",
          "forms": { "ich": "trinke", "du": "trinkst", "er/sie/es": "trinkt", "wir": "trinken", "ihr": "trinkt", "sie/Sie": "trinken" }
        },
        "perfekt": {
          "mood": "indicativ", "auxiliary_verb": "haben", "past_participle": "getrunken",
          "forms": { "ich": "habe getrunken", "du": "hast getrunken", "er/sie/es": "hat getrunken", "wir": "haben getrunken", "ihr": "habt getrunken", "sie/Sie": "haben getrunken" }
        },
        "präteritum": {
          "mood": "indicativ",
          "forms": { "ich": "trank", "du": "trankst", "er/sie/es": "trank", "wir": "tranken", "ihr": "trankt", "sie/Sie": "tranken" }
        },
        "futur I": {
          "mood": "indicativ", "auxiliary_verb": "werden",
          "forms": { "ich": "werde trinken", "du": "wirst trinken", "er/sie/es": "wird trinken", "wir": "werden trinken", "ihr": "werdet trinken", "sie/Sie": "werden trinken" }
        },
        "konjunktiv II": {
          "mood": "konjunktiv",
          "forms": { "ich": "tränke", "du": "tränkest", "er/sie/es": "tränke", "wir": "tränken", "ihr": "tränket", "sie/Sie": "tränken" }
        }
      }
    },
    {
      "infinitive": "sprechen",
      "translation_en": "to speak",
      "tags": ["irregular", "stem-vowel-change"],
      "tenses": {
        "präsens": {
          "mood": "indicativ",
          "forms": { "ich": "spreche", "du": "sprichst", "er/sie/es": "spricht", "wir": "sprechen", "ihr": "sprecht", "sie/Sie": "sprechen" }
        },
        "perfekt": {
          "mood": "indicativ", "auxiliary_verb": "haben", "past_participle": "gesprochen",
          "forms": { "ich": "habe gesprochen", "du": "hast gesprochen", "er/sie/es": "hat gesprochen", "wir": "haben gesprochen", "ihr": "habt gesprochen", "sie/Sie": "haben gesprochen" }
        },
        "präteritum": {
          "mood": "indicativ",
          "forms": { "ich": "sprach", "du": "sprachst", "er/sie/es": "sprach", "wir": "sprachen", "ihr": "spracht", "sie/Sie": "sprachen" }
        },
        "futur I": {
          "mood": "indicativ", "auxiliary_verb": "werden",
          "forms": { "ich": "werde sprechen", "du": "wirst sprechen", "er/sie/es": "wird sprechen", "wir": "werden sprechen", "ihr": "werdet sprechen", "sie/Sie": "werden sprechen" }
        },
        "konjunktiv II": {
          "mood": "konjunktiv",
          "forms": { "ich": "spräche", "du": "sprächest", "er/sie/es": "spräche", "wir": "sprächen", "ihr": "sprächet", "sie/Sie": "sprächen" }
        }
      }
    }
  ]
}
